oasis_gui/gui.py
oasis_gui/ui/resources/lock.png
oasis_gui/ui/resources/spin.gif
oasis_gui/ui/resources/unlock.png
oasis_gui/ui/resources/boards/OASIS-UROS.png
oasis_gui/ui/resources/boards/OASISV1.png
oasis_gui/ui/resources/boards/Unknown.png
oasis_gui/ui/resources/icons/128x128.png
oasis_gui/ui/resources/icons/16x16.png
oasis_gui/ui/resources/icons/24x24.png
oasis_gui/ui/resources/icons/256x256.png
oasis_gui/ui/resources/icons/32x32.png
oasis_gui/ui/resources/icons/48x48.png
oasis_gui/ui/resources/icons/64x64.png
oasis_gui-0.9.2.dist-info/licenses/LICENSE
oasis_gui-0.9.2.dist-info/METADATA
oasis_gui-0.9.2.dist-info/WHEEL
oasis_gui-0.9.2.dist-info/entry_points.txt
oasis_gui-0.9.2.dist-info/top_level.txt
oasis_gui-0.9.2.dist-info/RECORD
