Metadata-Version: 2.4
Name: oasis-gui
Version: 0.9.2
Summary: GUI for the Open Acquisition System for IEPE Sensors (OASIS)
Author-email: Johannes Maierhofer <j.maierhofer@tum.de>, Oliver Zobel <oliver.zobel@tum.de>
Project-URL: Homepage, https://gitlab.com/oasis-acquisition/oasis-gui
Classifier: Development Status :: 4 - Beta
Classifier: Intended Audience :: Science/Research
Classifier: Intended Audience :: Developers
Classifier: License :: OSI Approved :: MIT License
Classifier: Operating System :: OS Independent
Classifier: Programming Language :: Python :: 3
Classifier: Programming Language :: Python :: 3.11
Classifier: Programming Language :: Python :: 3.12
Classifier: Topic :: Scientific/Engineering
Classifier: Topic :: Software Development :: User Interfaces
Requires-Python: >=3.11
License-File: LICENSE
Requires-Dist: oasis-api
Requires-Dist: pyserial
Requires-Dist: numpy
Requires-Dist: pyqt6
Requires-Dist: pyqtgraph
Requires-Dist: h5py
Dynamic: license-file
